[
    {
        "guid": "d4319aa7-fbb9-45e1-979d-ad0e77e429aa",
        "name": "Jellyfin Upscaler",
        "description": "A plugin to enhance video quality through real-time upscaling for supported devices.",
        "overview": "Enhance video quality with real-time upscaling.",
        "owner": "Kuschel-code",
        "category": "VideoProcessing",
        "imageUrl": "https://raw.githubusercontent.com/Kuschel-code/JellyfinUpscalerRepo/main/addons/UpscalerPlugin/addon-image.png",
        "versions": [
            {
                "version": "1.0.0",
                "changelog": "Initial release",
                "targetAbi": "10.10.0.0",
                "sourceUrl": "https://raw.githubusercontent.com/Kuschel-code/JellyfinUpscalerRepo/main/addons/UpscalerPlugin/upscaler.zip",
                "checksum": "SHA256:F81E92F9D70ED06771E402D37D4C14BAD1B39C44CFB32435FD5622EDACB6EBCC",
                "timestamp": "2024-11-20T00:00:00Z"
            }
        ]
    }
]
